[
  {
    "uid": "acim-minute-2026-04-14",
    "updateDate": "2026-04-14T06:00:00.0Z",
    "titleText": "ACIM Daily Minute",
    "mainText": "Allegiance to the denial of God is the ego’s religion.The god of sickness obviously demands the denial of health because health is in direct opposition to its own survival. But consider what this means to YOU. UNLESS you are sick you cannot keep the gods you made, for only in sickness could you possibly WANT them. Blasphemy, then, is SELF-destructive, NOT God-destructive. It means that you are willing NOT to know yourself IN ORDER to be sick. This is the offering which your god demands because, having made him out of YOUR insanity, he is an insane idea. He has many forms, but although he may seem like many different things he is but one idea;– the denial of God. Sickness and death entered the mind of God’s Son AGAINST His Will.The attack on God made His Son think he was fatherless, and out of his depression he made the god of depression.This was his alternative to joy because he would not accept the fact that, although he was a creator, he had been created.Yet the Son IS helpless without the Father,Who alone is his Help.We said before that of yourselves you can do nothing, but you are not OF yourselves. If you were, what you have made would be true, and you could NEVER escape. It is BECAUSE you did not make yourselves that you need be troubled by nothing.Your gods are nothing because your Father did not create them.",
    "redirectionUrl": "https://www.acimdailyminute.org/daily-minute.html"
  }
]
