[
  {
    "uid": "acim-minute-2026-05-28",
    "updateDate": "2026-05-28T06:00:00.0Z",
    "titleText": "ACIM Daily Minute",
    "mainText": "This is in strict accord with vision’s fundamental law:You see what you believe is there, and you believe it there because you WANT it there. Perception has no other law than this.The rest but stems from this, to hold it up and offer it support. This is perception’s form, adapted to this world, of God’s more basic law; that love creates itself, and nothing BUT itself. God’s laws do not obtain directly to a world perception rules, for such a world could not have been created by the Mind to which perception has no meaning. Yet are His laws reflected everywhere. Not that the world where this reflection is is real at all. Only because His Son believes it is, and from His Son’s belief He could not let Himself be separate entirely. He could not enter His Son’s insanity with him, but He could be sure His sanity went there with him, so he could not be lost forever in the madness of his wish. Perception rests on choosing; knowledge does not. Knowledge has but one law because it has but One Creator. But this world has two who made it, and they do not see it as the same.To each it has a different purpose, and to each it is a perfect means to serve the goal for which it is perceived.",
    "redirectionUrl": "https://www.acimdailyminute.org/daily-minute.html"
  }
]
