{
  "lesson_id": 9,
  "date": "2026-04-13",
  "title": "“I see nothing as it is now.”",
  "text": "“I see nothing as it is now.”\nThis idea obviously follows from the two preceding ones. But while\nyou may be able to accept it intellectually, it is unlikely that it will\nmean anything to you as yet. However, understanding is not necessary\nat this point. In fact, the recognition that you do not understand is a\nprerequisite for undoing your false ideas. These exercises are\nconcerned with practice, not with understanding.You do not need to\npractice what you really understand. It would indeed be circular to\naim at understanding, and assume that you have it already.\n      It is difficult for the untrained mind to believe that what seems\nto be pictured before it is not there.This idea can be quite disturbing,\nand may meet with active resistance in any number of forms.Yet that\ndoes not preclude applying it. No more than that is required for these\nor any other exercises. Each little step will clear a little of the darkness\naway, and understanding will finally come to lighten every corner of\nthe mind which has been cleared of the debris that darkens it.\n      These exercises, for which three or four practice periods are\nsufficient, involve looking about you and applying the idea for the day\nto whatever you see, remembering the need for its indiscriminate\napplication, and the essential rule of excluding nothing. It is\nemphasized again that while complete inclusion should not be\nattempted, specific exclusion must be avoided. Be sure you are honest\nin making this distinction.You may be tempted to obscure it.\n     For example:\n     “I do not see this typewriter as it is now.”\n     “I do not see this key as it is now.”\n     “I do not see this telephone as it is now.”\nBegin with things that are nearest you, and then extend the range:\n     “I do not see that coat rack as it is now.”\n     “I do not see that face as it is now.”\n     “I do not see that door as it is now.”",
  "word_count": 331,
  "audio_url": "audio/daily-lessons/lesson-009.mp3",
  "youtube_url": "https://youtube.com/watch?v=lSIAdQyn8WM",
  "youtube_id": "lSIAdQyn8WM",
  "total_lessons": 365,
  "archive": [
    {
      "lesson_id": 8,
      "title": "“My mind is preoccupied with past thoughts.”",
      "date": "2026-04-10",
      "audio_url": "audio/daily-lessons/lesson-008.mp3"
    },
    {
      "lesson_id": 7,
      "title": "I see only the past.",
      "date": "2026-04-09",
      "audio_url": "audio/daily-lessons/lesson-007.mp3"
    },
    {
      "lesson_id": 6,
      "title": "I am upset because I see something that is not there.",
      "date": "2026-04-07",
      "audio_url": "audio/daily-lessons/lesson-006.mp3"
    },
    {
      "lesson_id": 5,
      "title": "I am never upset for the reason I think.",
      "date": "2026-04-06",
      "audio_url": "audio/daily-lessons/lesson-005.mp3"
    },
    {
      "lesson_id": 4,
      "title": "These thoughts do not mean anything.",
      "date": "2026-04-03",
      "audio_url": "audio/daily-lessons/lesson-004.mp3"
    },
    {
      "lesson_id": 3,
      "title": "I do not understand anything I see in this room.",
      "date": "2026-04-02",
      "audio_url": "audio/daily-lessons/lesson-003.mp3"
    }
  ]
}
