{
  "timestamp": "2026-05-09T07:21:27.455901+00:00",
  "uptime_start": null,
  "uptime_seconds": 0,
  "streams": {
    "daily_minute": {
      "status": "completed",
      "last_updated": "2026-05-09",
      "segment_id": 12847,
      "episodes_published": 12847
    },
    "daily_lessons": {
      "status": "completed",
      "last_updated": "2026-05-08",
      "lesson_id": 27,
      "episodes_published": 27
    },
    "text_series": {
      "status": "coming_soon",
      "estimated_start": "Late 2027"
    }
  },
  "api_costs": {
    "today": {
      "elevenlabs": {
        "calls": 1,
        "cost_usd": 0.03726,
        "details": {
          "characters": 1242
        }
      }
    },
    "total_usd": 0.0373,
    "month_estimate_usd": 2.48,
    "daily_budget": 0.32,
    "budget_pct": 11.6
  },
  "status": {
    "state": "idle",
    "stream_health": "online",
    "next_cycle_minutes": null,
    "degraded_services": []
  },
  "feeds": {
    "feed_xml": "https://www.acimdailyminute.org/feed.xml",
    "podcast_minute": "https://www.acimdailyminute.org/podcast-minute.xml",
    "podcast_lessons": "https://www.acimdailyminute.org/podcast-lessons.xml",
    "alexa": "https://www.acimdailyminute.org/alexa.json"
  }
}
