{
  "timestamp": "2026-05-21T07:22:57.647938+00:00",
  "uptime_start": null,
  "uptime_seconds": 0,
  "streams": {
    "daily_minute": {
      "status": "completed",
      "last_updated": "2026-05-21",
      "segment_id": 12089,
      "episodes_published": 12089
    },
    "daily_lessons": {
      "status": "completed",
      "last_updated": "2026-05-20",
      "lesson_id": 35,
      "episodes_published": 35
    },
    "text_series": {
      "status": "coming_soon",
      "estimated_start": "Late 2027"
    }
  },
  "api_costs": {
    "today": {
      "elevenlabs": {
        "calls": 1,
        "cost_usd": 0.0396,
        "details": {
          "characters": 1320
        }
      }
    },
    "total_usd": 0.0396,
    "month_estimate_usd": 2.54,
    "daily_budget": 0.32,
    "budget_pct": 12.3
  },
  "status": {
    "state": "idle",
    "stream_health": "online",
    "next_cycle_minutes": null,
    "degraded_services": []
  },
  "feeds": {
    "feed_xml": "https://www.acimdailyminute.org/feed.xml",
    "podcast_minute": "https://www.acimdailyminute.org/podcast-minute.xml",
    "podcast_lessons": "https://www.acimdailyminute.org/podcast-lessons.xml",
    "alexa": "https://www.acimdailyminute.org/alexa.json"
  }
}
